colors/__init__.py
Terminal_Colorify-1.1.1.dist-info/LICENSE
Terminal_Colorify-1.1.1.dist-info/METADATA
Terminal_Colorify-1.1.1.dist-info/WHEEL
Terminal_Colorify-1.1.1.dist-info/top_level.txt
Terminal_Colorify-1.1.1.dist-info/RECORD
