Metadata-Version: 2.1
Name: Terminal-Colorify
Version: 1.1.1
Summary: A simple Python module for adding colors to text in the terminal
Author: amiryona
Author-email: amiryona6@gmail.com
Classifier: Programming Language :: Python :: 3
Classifier: License :: OSI Approved :: MIT License
Classifier: Operating System :: OS Independent
Requires-Python: >=3.6
License-File: LICENSE
